docker_run/plugins/docker_ros.py
docker_run_docker_ros-1.0.9.dist-info/licenses/LICENSE
docker_run_docker_ros-1.0.9.dist-info/METADATA
docker_run_docker_ros-1.0.9.dist-info/WHEEL
docker_run_docker_ros-1.0.9.dist-info/top_level.txt
docker_run_docker_ros-1.0.9.dist-info/RECORD
