Metadata-Version: 2.4
Name: docker-run-docker-ros
Version: 1.0.9
Summary: docker-run plugin for Docker images built by docker-ros
Author-email: Lennart Reiher <lennart.reiher@rwth-aachen.de>, Jean-Pierre Busch <jean-pierre.busch@rwth-aachen.de>
Maintainer-email: Lennart Reiher <lennart.reiher@rwth-aachen.de>, Jean-Pierre Busch <jean-pierre.busch@rwth-aachen.de>
License: MIT License
Project-URL: Repository, https://github.com/ika-rwth-aachen/docker-run
Project-URL: Bug Tracker, https://github.com/ika-rwth-aachen/docker-run/issues
Keywords: docker,container,ros
Classifier: License :: OSI Approved :: MIT License
Classifier: Programming Language :: Python
Classifier: Programming Language :: Python :: 3
Classifier: Operating System :: POSIX :: Linux
Requires-Python: >=3.7
License-File: LICENSE
Requires-Dist: docker-run-cli>=0.10.2
Dynamic: license-file
